py_mpesa_daraja_api/__init__.py
py_mpesa_daraja_api/auth.py
py_mpesa_daraja_api/mpesa.py
py_mpesa_daraja_api/mpesa_models.py
py_mpesa_daraja_api/mpesa_urls.py
py_mpesa_daraja_api/utils/__init__.py
py_mpesa_daraja_api/utils/utils.py
py_mpesa_daraja_api-0.0.1.dist-info/LICENSE.txt
py_mpesa_daraja_api-0.0.1.dist-info/METADATA
py_mpesa_daraja_api-0.0.1.dist-info/WHEEL
py_mpesa_daraja_api-0.0.1.dist-info/top_level.txt
py_mpesa_daraja_api-0.0.1.dist-info/RECORD
