Metadata-Version: 2.1
Name: py_mpesa_daraja_api
Version: 0.0.1
Summary: Mpesa library that can be used to make api calls to mpesa daraja API
Home-page: https://github.com/juniorfelix998/pympesa
Author: Felix Okoth
Author-email: juniorfelix998@gmail.com
License: MIT
Classifier: License :: OSI Approved :: MIT License
Classifier: Programming Language :: Python :: 3.10
Classifier: Operating System :: OS Independent
Requires-Python: >=3.10
License-File: LICENSE.txt
Requires-Dist: pydantic
Requires-Dist: requests
Provides-Extra: dev
Requires-Dist: twine >=5.1.0 ; extra == 'dev'
